lf/__init__.py
lf/data.py
lf/nanfinder.py
lf/quality.py
lf/utils.py
lf/data/__init__.py
lf/data/rx.py
lf/data/rxquality.py
lfdata-0.0.4.dist-info/LICENSE
lfdata-0.0.4.dist-info/METADATA
lfdata-0.0.4.dist-info/WHEEL
lfdata-0.0.4.dist-info/top_level.txt
lfdata-0.0.4.dist-info/RECORD
