Metadata-Version: 2.1
Name: lfdata
Version: 0.0.4
Summary: Tools for interacting with GT's LF AWESOME Receiver data
Home-page: https://github.gatech.edu/LF-Group/lfdata
Author: David Richardson
Author-email: drichardson42@gatech.edu
License: UNKNOWN
Platform: UNKNOWN
Classifier: Programming Language :: Python :: 3
Classifier: Programming Language :: Python :: 3.6
Classifier: Programming Language :: Python :: 3.7
Classifier: License :: OSI Approved :: GNU General Public License v3 or later (GPLv3+)
Classifier: Development Status :: 2 - Pre-Alpha
Classifier: Intended Audience :: Science/Research
Requires-Dist: scipy
Requires-Dist: numpy
Requires-Dist: sklearn
Provides-Extra: dev
Requires-Dist: twine ; extra == 'dev'
